atlaspy/__init__.py
atlaspy/core.py
atlaspy/source_data/.DS_Store
atlaspy/source_data/atlases/.DS_Store
atlaspy/source_data/atlases/luts/.DS_Store
atlaspy/source_data/atlases/luts/aal.csv
atlaspy/source_data/atlases/luts/bna.csv
atlaspy/source_data/atlases/luts/dkt.csv
atlaspy/source_data/atlases/luts/ho.csv
atlaspy/source_data/atlases/luts/sch400.csv
atlaspy/source_data/atlases/niftis/.DS_Store
atlaspy/source_data/atlases/niftis/aal.nii.gz
atlaspy/source_data/atlases/niftis/bna.nii.gz
atlaspy/source_data/atlases/niftis/dkt.nii.gz
atlaspy/source_data/atlases/niftis/ho.nii.gz
atlaspy/source_data/atlases/niftis/sch400.nii.gz
atlaspy/source_data/atlases/niftis/vep.nii.gz
atlaspy-0.0.8.dist-info/METADATA
atlaspy-0.0.8.dist-info/WHEEL
atlaspy-0.0.8.dist-info/top_level.txt
atlaspy-0.0.8.dist-info/RECORD
