Metadata-Version: 2.1
Name: atlaspy
Version: 0.0.8
Summary: Python library for working with brain atlases
Author: Alfredo Lucas
Author-email: alfredo1238@gmail.com
Classifier: License :: OSI Approved :: MIT License
Classifier: Programming Language :: Python
Classifier: Programming Language :: Python :: 3.8
Requires-Dist: pyvista
Requires-Dist: seaborn
Requires-Dist: pandas
Requires-Dist: matplotlib
Requires-Dist: nibabel
Requires-Dist: nilearn
